.env.example
.envrc
AUTHORS
ChangeLog
LICENSE.md
Makefile
README.md
setup.cfg
setup.py
examples/greeter/greeter
examples/greeter/greeter.py
examples/greeter/requirements.txt
examples/slack/requirements.txt
examples/slack/slack
examples/slack/slack.py
fly_cli/__init__.py
fly_cli.egg-info/PKG-INFO
fly_cli.egg-info/SOURCES.txt
fly_cli.egg-info/dependency_links.txt
fly_cli.egg-info/entry_points.txt
fly_cli.egg-info/not-zip-safe
fly_cli.egg-info/pbr.json
fly_cli.egg-info/requires.txt
fly_cli.egg-info/top_level.txt
tests/conftest.py
tests/test_fly_cli.py