Metadata-Version: 2.1
Name: fly-cli
Version: 0.1.1
Summary: Invoke class methods from the command-line.
Home-page: https://github.com/datashaman/fly-cli
Author: datashaman
Author-email: marlinf@datashaman.com
License: mit
Platform: UNKNOWN
Classifier: Development Status :: 3 - Alpha
Classifier: Environment :: Console
Classifier: Intended Audience :: Developers
Classifier: Intended Audience :: Information Technology
Classifier: License :: OSI Approved :: MIT License
Classifier: Operating System :: OS Independent
Classifier: Programming Language :: Python
Provides-Extra: develop
